odoo/addons/l10n_es_aeat_mod115/README.rst
odoo/addons/l10n_es_aeat_mod115/__init__.py
odoo/addons/l10n_es_aeat_mod115/__manifest__.py
odoo/addons/l10n_es_aeat_mod115/data/aeat_export_mod115_data.xml
odoo/addons/l10n_es_aeat_mod115/data/tax_code_map_mod115_data.xml
odoo/addons/l10n_es_aeat_mod115/docs/DR115e15v11.xls
odoo/addons/l10n_es_aeat_mod115/i18n/bg.po
odoo/addons/l10n_es_aeat_mod115/i18n/ca.po
odoo/addons/l10n_es_aeat_mod115/i18n/cs.po
odoo/addons/l10n_es_aeat_mod115/i18n/es.po
odoo/addons/l10n_es_aeat_mod115/i18n/es_CO.po
odoo/addons/l10n_es_aeat_mod115/i18n/es_CR.po
odoo/addons/l10n_es_aeat_mod115/i18n/eu.po
odoo/addons/l10n_es_aeat_mod115/i18n/fr.po
odoo/addons/l10n_es_aeat_mod115/i18n/gl.po
odoo/addons/l10n_es_aeat_mod115/i18n/hr.po
odoo/addons/l10n_es_aeat_mod115/i18n/l10n_es_aeat_mod115.pot
odoo/addons/l10n_es_aeat_mod115/i18n/nl.po
odoo/addons/l10n_es_aeat_mod115/i18n/pl.po
odoo/addons/l10n_es_aeat_mod115/i18n/pt.po
odoo/addons/l10n_es_aeat_mod115/i18n/pt_BR.po
odoo/addons/l10n_es_aeat_mod115/i18n/ru.po
odoo/addons/l10n_es_aeat_mod115/i18n/sl.po
odoo/addons/l10n_es_aeat_mod115/i18n/sv.po
odoo/addons/l10n_es_aeat_mod115/i18n/tr.po
odoo/addons/l10n_es_aeat_mod115/i18n/vi.po
odoo/addons/l10n_es_aeat_mod115/models/__init__.py
odoo/addons/l10n_es_aeat_mod115/models/mod115.py
odoo/addons/l10n_es_aeat_mod115/readme/CONTRIBUTORS.rst
odoo/addons/l10n_es_aeat_mod115/readme/DESCRIPTION.rst
odoo/addons/l10n_es_aeat_mod115/readme/USAGE.rst
odoo/addons/l10n_es_aeat_mod115/security/ir.model.access.csv
odoo/addons/l10n_es_aeat_mod115/security/l10n_es_aeat_mod115_security.xml
odoo/addons/l10n_es_aeat_mod115/static/description/icon.png
odoo/addons/l10n_es_aeat_mod115/static/description/icon_source.svg
odoo/addons/l10n_es_aeat_mod115/static/description/index.html
odoo/addons/l10n_es_aeat_mod115/tests/__init__.py
odoo/addons/l10n_es_aeat_mod115/tests/test_l10n_es_aeat_mod115.py
odoo/addons/l10n_es_aeat_mod115/views/mod115_view.xml
odoo12_addon_l10n_es_aeat_mod115-12.0.1.4.0.dist-info/METADATA
odoo12_addon_l10n_es_aeat_mod115-12.0.1.4.0.dist-info/WHEEL
odoo12_addon_l10n_es_aeat_mod115-12.0.1.4.0.dist-info/top_level.txt
odoo12_addon_l10n_es_aeat_mod115-12.0.1.4.0.dist-info/RECORD
